[
  {
    "book":"Genesis",
    "fileName":"Genesis.JSON"
  },
  {
    "book":"Exodus",
    "fileName":"Exodus.JSON"
  },
  {
    "book":"Leviticus",
    "fileName":"Leviticus.JSON"
  },
  {
    "book":"Numbers",
    "fileName":"Numbers.JSON"
  },
  {
    "book":"Deuteronomy",
    "fileName":"Deuteronomy.JSON"
  },
  {
    "book":"Joshua",
    "fileName":"Joshua.JSON"
  },
  {
    "book":"Judges",
    "fileName":"Judges.JSON"
  },
  {
    "book":"Ruth",
    "fileName":"Ruth.JSON"
  },
  {
    "book":"1 Samuel",
    "fileName":"1Samuel.JSON"
  },
  {
    "book":"2 Samuel",
    "fileName":"2Samuel.JSON"
  },
  {
    "book":"1 Kings",
    "fileName":"1Kings.JSON"
  },
  {
    "book":"2 Kings",
    "fileName":"2Kings.JSON"
  },
  {
    "book":"1 Chronicle",
    "fileName":"1Chronicles.JSON"
  },
  {
    "book":"2 Chronicle",
    "fileName":"2Chronicles.JSON"
  },
  {
    "book":"Ezra",
    "fileName":"Ezra.JSON"
  },
 {
    "book":"Nehemiah",
    "fileName":"Nehemiah.JSON"
  },
  {
    "book":"Esther",
    "fileName":"Esther.JSON"
  },
  {
    "book":"Job",
    "fileName":"Job.JSON"
  },
  {
    "book":"Psalms",
    "fileName":"Psalms.JSON"
  },
  {
    "book":"Proverbs",
    "fileName":"Proverbs.JSON"
  },
  {
    "book":"Ecclesiastes",
    "fileName":"Ecclesiastes.JSON"
  },
  {
    "book":"Song of Solomon",
    "fileName":"SongofSolomon.JSON"
  },
  {
    "book":"Isaiah",
    "fileName":"Isaiah.JSON"
  },
  {
    "book":"Jeremiah",
    "fileName":"Jeremiah.JSON"
  },
  {
    "book":"Lamentations",
    "fileName":"Lamentations.JSON"
  },
  {
    "book":"Ezekiel",
    "fileName":"Ezekiel.JSON"
  },
  {
    "book":"Daniel",
    "fileName":"Daniel.JSON"
  },
  {
    "book":"Hosea",
    "fileName":"Hosea.JSON"
  },
  {
    "book":"Joel",
    "fileName":"Joel.JSON"
  },
  {
    "book":"Amos",
    "fileName":"Amos.JSON"
  },
  {
    "book":"Obadiah",
    "fileName":"Obadiah.JSON"
  },
  {
    "book":"Jonah",
    "fileName":"Jonah.JSON"
  },
  {
    "book":"Micah",
    "fileName":"Micah.JSON"
  },
  {
    "book":"Nahum",
    "fileName":"Nahum.JSON"
  },
  {
    "book":"Habakkuk",
    "fileName":"Habakkuk.JSON"
  },
  {
    "book":"Zephaniah",
    "fileName":"Zephaniah.JSON"
  },
  {
    "book":"Haggai",
    "fileName":"Haggai.JSON"
  },
  {
    "book":"Zechariah",
    "fileName":"Zechariah.JSON"
  },
  {
    "book":"Malachi",
    "fileName":"Malachi.JSON"
  },
  {
    "book":"Matthew",
    "fileName":"Matthew.JSON"
  },
  {
    "book":"Mark",
    "fileName":"Mark.JSON"
  },
  {
    "book":"Luke",
    "fileName":"Luke.JSON"
  },
  {
    "book":"John",
    "fileName":"John.JSON"
  },
  {
    "book":"Acts",
    "fileName":"Acts.JSON"
  },
  {
    "book":"Romans",
    "fileName":"Romans.JSON"
  },{
    "book":"1 Corinthians",
    "fileName":"1Corinthians.JSON"
  },{
    "book":"2 Corinthians",
    "fileName":"2 Corinthians.JSON"
  },
  {
    "book":"Galatians",
    "fileName":"Galatians.JSON"
  },
   {
    "book":"Ephesians",
    "fileName":"Ephesians.JSON"
  },
   {
    "book":"Philippians",
    "fileName":"Philippians.JSON"
  },
  {
    "book":"Colossians",
    "fileName":"Colossians.JSON"
  }, 
  {
    "book":"1 Thessalonians",
    "fileName":"1Thessalonians.JSON"
  }, 
  {
    "book":"2 Thessalonians",
    "fileName":"2Thessalonians.JSON"
  },
   {
    "book":"1 Timothy",
    "fileName":"1Timothy.JSON"
  },
   {
    "book":"2 Timothy",
    "fileName":"2Timothy.JSON"
  },
  {
    "book":"Titus",
    "fileName":"Titus.JSON"
  }, 
  {
    "book":"Philemon",
    "fileName":"Philemon.JSON"
  }, 
  {
    "book":"Hebrews",
    "fileName":"Hebrews.JSON"
  },
  {
    "book":"James",
    "fileName":"James.JSON"
  },
  {
    "book":"1 Peter",
    "fileName":"1Peter.JSON"
  },
  {
    "book":"2 Peter",
    "fileName":"2Peter.JSON"
  },
  {
    "book":"1 John",
    "fileName":"1John.JSON"
  },
  {
    "book":"2 John",
    "fileName":"2John.JSON"
  },
  {
    "book":"3 John",
    "fileName":"3John.JSON"
  },
  {
    "book":"Jude",
    "fileName":"Jude.JSON"
  },
  {
    "book":"Revelation",
    "fileName":"Revelation.JSON"
  }
  
]
